autoclean_view/__init__.py
autoclean_view/cli.py
autoclean_view/viewer.py
autocleaneeg_view/__init__.py
autocleaneeg_view/cli.py
autocleaneeg_view/viewer.py
autocleaneeg_view/loaders/__init__.py
autocleaneeg_view/loaders/bdf.py
autocleaneeg_view/loaders/brainvision.py
autocleaneeg_view/loaders/edf.py
autocleaneeg_view/loaders/eeglab.py
autocleaneeg_view/loaders/egi.py
autocleaneeg_view/loaders/fif.py
autocleaneeg_view/loaders/gdf.py
autocleaneeg_view/loaders/neuronexus.py
autocleaneeg_view/loaders/neuronexus_remap.py
autocleaneeg_view-0.1.6.dist-info/licenses/LICENSE
autocleaneeg_view-0.1.6.dist-info/METADATA
autocleaneeg_view-0.1.6.dist-info/WHEEL
autocleaneeg_view-0.1.6.dist-info/entry_points.txt
autocleaneeg_view-0.1.6.dist-info/top_level.txt
autocleaneeg_view-0.1.6.dist-info/RECORD
