Metadata-Version: 2.4
Name: autocleaneeg-view
Version: 0.1.6
Summary: A lightweight tool for viewing EEGLAB .set files using MNE-QT Browser
Author: AutoClean Team
License: MIT
Requires-Python: >=3.9
License-File: LICENSE
Requires-Dist: mne>=1.7
Requires-Dist: mne-qt-browser>=0.5.2
Requires-Dist: click>=8.0
Requires-Dist: pyqt5; sys_platform == "darwin"
Requires-Dist: neo>=0.13
Requires-Dist: quantities>=0.14
Dynamic: license-file
